tk_notepad/__init__.py
tk_notepad/notepad.py
tk_notepad/icons/notepad_icon.ico
tk_notepad-0.5.dist-info/LICENSE
tk_notepad-0.5.dist-info/METADATA
tk_notepad-0.5.dist-info/WHEEL
tk_notepad-0.5.dist-info/entry_points.txt
tk_notepad-0.5.dist-info/top_level.txt
tk_notepad-0.5.dist-info/RECORD
