Metadata-Version: 2.1
Name: tk-notepad
Version: 0.5
Summary: tk-notepad is a notepad program developed with Tkinter, equipped with a simple interface.
Home-page: https://github.com/ryanvij/tk-notepad
Author: ryanvij
Author-email: ryan.vijay2006@gmail.com
License: MIT
Platform: UNKNOWN
Requires-Python: >=3.4
License-File: LICENSE
